{
  "updated_at": "2026-05-13T16:00:02",
  "updated_label": "13/05/2026 16:00",
  "source": "https://client.yalecom.co.th/custom_menu/extension_summary_outbound",
  "row_count": 8,
  "rows": [
    {
      "extension": "302",
      "name": "เตย",
      "total_calls": 82,
      "answered": 51,
      "missed": 29,
      "talktime": 9025,
      "avg": 176,
      "_raw": [
        "302",
        "เตย",
        "82",
        "51",
        "29",
        "2",
        "0:34:54",
        "2:30:25",
        "32",
        "10",
        "41"
      ],
      "_headers": [
        "หมายเลข",
        "ชื่อ",
        "จำนวนสาย",
        "รับสาย",
        "ไม่รับสาย",
        "ไม่สำเร็จ",
        "รอสายรวม",
        "ระยะเวลาคุยสาย",
        "คุยเกิน30วิ",
        "จำนวนวางสายก่อน",
        "จำนวนถูกตัดสาย"
      ],
      "delta": 1515
    },
    {
      "extension": "305",
      "name": "เจ",
      "total_calls": 126,
      "answered": 86,
      "missed": 40,
      "talktime": 7044,
      "avg": 81,
      "_raw": [
        "305",
        "เจ",
        "126",
        "86",
        "40",
        "0",
        "0:55:05",
        "1:57:24",
        "46",
        "16",
        "70"
      ],
      "_headers": [
        "หมายเลข",
        "ชื่อ",
        "จำนวนสาย",
        "รับสาย",
        "ไม่รับสาย",
        "ไม่สำเร็จ",
        "รอสายรวม",
        "ระยะเวลาคุยสาย",
        "คุยเกิน30วิ",
        "จำนวนวางสายก่อน",
        "จำนวนถูกตัดสาย"
      ],
      "delta": 1953
    },
    {
      "extension": "308",
      "name": "อุ๋ย",
      "total_calls": 115,
      "answered": 78,
      "missed": 36,
      "talktime": 5949,
      "avg": 76,
      "_raw": [
        "308",
        "อุ๋ย",
        "115",
        "78",
        "36",
        "1",
        "0:57:15",
        "1:39:09",
        "47",
        "26",
        "52"
      ],
      "_headers": [
        "หมายเลข",
        "ชื่อ",
        "จำนวนสาย",
        "รับสาย",
        "ไม่รับสาย",
        "ไม่สำเร็จ",
        "รอสายรวม",
        "ระยะเวลาคุยสาย",
        "คุยเกิน30วิ",
        "จำนวนวางสายก่อน",
        "จำนวนถูกตัดสาย"
      ],
      "delta": 534
    },
    {
      "extension": "304",
      "name": "นุช",
      "total_calls": 86,
      "answered": 60,
      "missed": 26,
      "talktime": 5844,
      "avg": 97,
      "_raw": [
        "304",
        "นุช",
        "86",
        "60",
        "26",
        "0",
        "0:40:40",
        "1:37:24",
        "34",
        "25",
        "35"
      ],
      "_headers": [
        "หมายเลข",
        "ชื่อ",
        "จำนวนสาย",
        "รับสาย",
        "ไม่รับสาย",
        "ไม่สำเร็จ",
        "รอสายรวม",
        "ระยะเวลาคุยสาย",
        "คุยเกิน30วิ",
        "จำนวนวางสายก่อน",
        "จำนวนถูกตัดสาย"
      ],
      "delta": 1491
    },
    {
      "extension": "303",
      "name": "วุฒิ",
      "total_calls": 63,
      "answered": 37,
      "missed": 26,
      "talktime": 5802,
      "avg": 156,
      "_raw": [
        "303",
        "วุฒิ",
        "63",
        "37",
        "26",
        "0",
        "0:35:21",
        "1:36:42",
        "24",
        "19",
        "18"
      ],
      "_headers": [
        "หมายเลข",
        "ชื่อ",
        "จำนวนสาย",
        "รับสาย",
        "ไม่รับสาย",
        "ไม่สำเร็จ",
        "รอสายรวม",
        "ระยะเวลาคุยสาย",
        "คุยเกิน30วิ",
        "จำนวนวางสายก่อน",
        "จำนวนถูกตัดสาย"
      ],
      "delta": 1134
    },
    {
      "extension": "306",
      "name": "หน่อง",
      "total_calls": 85,
      "answered": 61,
      "missed": 23,
      "talktime": 5316,
      "avg": 87,
      "_raw": [
        "306",
        "หน่อง",
        "85",
        "61",
        "23",
        "1",
        "0:42:10",
        "1:28:36",
        "33",
        "15",
        "46"
      ],
      "_headers": [
        "หมายเลข",
        "ชื่อ",
        "จำนวนสาย",
        "รับสาย",
        "ไม่รับสาย",
        "ไม่สำเร็จ",
        "รอสายรวม",
        "ระยะเวลาคุยสาย",
        "คุยเกิน30วิ",
        "จำนวนวางสายก่อน",
        "จำนวนถูกตัดสาย"
      ],
      "delta": 827
    },
    {
      "extension": "309",
      "name": "ซิน",
      "total_calls": 107,
      "answered": 54,
      "missed": 53,
      "talktime": 4473,
      "avg": 82,
      "_raw": [
        "309",
        "ซิน",
        "107",
        "54",
        "53",
        "0",
        "0:35:57",
        "1:14:33",
        "29",
        "28",
        "26"
      ],
      "_headers": [
        "หมายเลข",
        "ชื่อ",
        "จำนวนสาย",
        "รับสาย",
        "ไม่รับสาย",
        "ไม่สำเร็จ",
        "รอสายรวม",
        "ระยะเวลาคุยสาย",
        "คุยเกิน30วิ",
        "จำนวนวางสายก่อน",
        "จำนวนถูกตัดสาย"
      ],
      "delta": 815
    },
    {
      "extension": "307",
      "name": "กัน",
      "total_calls": 81,
      "answered": 27,
      "missed": 46,
      "talktime": 2598,
      "avg": 96,
      "_raw": [
        "307",
        "กัน",
        "81",
        "27",
        "46",
        "8",
        "0:48:46",
        "0:43:18",
        "16",
        "18",
        "9"
      ],
      "_headers": [
        "หมายเลข",
        "ชื่อ",
        "จำนวนสาย",
        "รับสาย",
        "ไม่รับสาย",
        "ไม่สำเร็จ",
        "รอสายรวม",
        "ระยะเวลาคุยสาย",
        "คุยเกิน30วิ",
        "จำนวนวางสายก่อน",
        "จำนวนถูกตัดสาย"
      ],
      "delta": 1001
    }
  ]
}